{"name":"Diligenciamiento exitoso del formulario de autenticación, no se presenta ningún mensaje de validación.","id":"como-usuario-de-la-plataforma--requiero-validar-la-creación-de-un-post--tambien-de-algunos-escenarios-alternos;diligenciamiento-exitoso-del-formulario-de-autenticación--no-se-presenta-ningún-mensaje-de-validación.","testSteps":[{"number":1,"description":"Given Ingreso a la plataforma  opensourcecms","duration":4659,"startTime":"2020-11-18T01:40:51.687-05:00[America/Bogota]","result":"SUCCESS","precondition":false,"level":0,"children":[{"number":2,"description":"Carlos enter","duration":4287,"startTime":"2020-11-18T01:40:52.057-05:00[America/Bogota]","result":"SUCCESS","precondition":false,"level":1,"children":[{"number":3,"description":"Carlos opens the Sources cms page posts","duration":4255,"startTime":"2020-11-18T01:40:52.084-05:00[America/Bogota]","result":"SUCCESS","precondition":false,"level":2}]}]},{"number":4,"description":"When Me autentico con usuario \"opensourcecms\" y clave \"opensourcecms\"","duration":3348,"startTime":"2020-11-18T01:40:56.348-05:00[America/Bogota]","result":"SUCCESS","precondition":false,"level":0,"children":[{"number":5,"description":"Carlos enters \u0027opensourcecms\u0027 into Campo de texto usuario","duration":334,"startTime":"2020-11-18T01:40:56.367-05:00[America/Bogota]","result":"SUCCESS","precondition":false,"level":1},{"number":6,"description":"Carlos enters \u0027opensourcecms\u0027 into Campo de texto contraseña","duration":285,"startTime":"2020-11-18T01:40:56.714-05:00[America/Bogota]","result":"SUCCESS","precondition":false,"level":1},{"number":7,"description":"Carlos clicks on Button make to login","duration":2687,"startTime":"2020-11-18T01:40:57.007-05:00[America/Bogota]","result":"SUCCESS","precondition":false,"level":1}]},{"number":8,"description":"Then Verifico ingreso exitoso con usuario \"opensourcecms\"","duration":224,"startTime":"2020-11-18T01:40:59.698-05:00[America/Bogota]","result":"SUCCESS","precondition":false,"level":0,"children":[{"number":9,"description":"Then the username should be \u0027opensourcecms\u0027","duration":41,"startTime":"2020-11-18T01:40:59.879-05:00[America/Bogota]","result":"SUCCESS","precondition":false,"level":1}]}],"userStory":{"id":"como-usuario-de-la-plataforma--requiero-validar-la-creación-de-un-post--tambien-de-algunos-escenarios-alternos","storyName":"Como usuario de la plataforma, requiero validar la creación de un post, tambien de algunos escenarios alternos","path":"posts.feature","type":"feature"},"featureTag":{"name":"Como usuario de la plataforma, requiero validar la creación de un post, tambien de algunos escenarios alternos","type":"feature","displayName":"Como usuario de la plataforma, requiero validar la creación de un post, tambien de algunos escenarios alternos"},"title":"Diligenciamiento exitoso del formulario de autenticación, no se presenta ningún mensaje de validación.","tags":[{"name":"Regression","type":"tag","displayName":"Regression"},{"name":"Como usuario de la plataforma, requiero validar la creación de un post, tambien de algunos escenarios alternos","type":"feature","displayName":"Como usuario de la plataforma, requiero validar la creación de un post, tambien de algunos escenarios alternos"}],"startTime":"2020-11-18T01:40:51.469-05:00[America/Bogota]","duration":8454,"projectKey":"","sessionId":"c90fcdccdfa4158ba7b0634673f61998","driver":"chrome","isManualTestingUpToDate":false,"manual":false,"testSource":"Cucumber","actors":[{"name":"Carlos","can":["browse the web"]}],"result":"SUCCESS"}